Hack4u/__init__.py
Hack4u/courses.py
Hack4u/utils.py
exeriop-0.1.0.dist-info/METADATA
exeriop-0.1.0.dist-info/WHEEL
exeriop-0.1.0.dist-info/top_level.txt
exeriop-0.1.0.dist-info/RECORD
