Metadata-Version: 2.1
Name: exeriop
Version: 0.1.0
Summary: Una biblioteca para consultar cursos de Hack4u.
Home-page: https://Hack4u.io
Author: Ezequiel Riofrio
